Workbook

Sheet 00 Introduction
A1: Enterprise AI Security & Governance Checklist
A2: Created by Hamza Saleem
A4: Purpose
A5: This workbook helps organisations adopt AI safely by assessing governance, security, privacy, detection, and operational controls across enterprise AI usage, LLM applications, AI coding tools, RAG systems, and agentic workflows.
A7: The problem this tool solves
A8: Employees and teams are adopting tools such as ChatGPT, Claude, Gemini, Copilot, AI coding assistants, browser extensions, and AI SaaS faster than security controls can mature. This creates risks around sensitive data leakage, Shadow AI, prompt injection, unsafe agent actions, weak logging, and inconsistent governance.
A10: How to use it
A11: 1. Start with AI Asset Inventory to identify where AI is being used.
A12: 2. Use the Control Checklist to score maturity and collect evidence.
A13: 3. Use the Guardrails Matrix and Detection Library to design practical controls.
A14: 4. Use Vendor Review and Incident Playbook tabs for third-party AI and response readiness.
A16: Author profile
A17: Hamza Saleem is a cybersecurity professional with a decade of experience across GRC, application security, penetration testing, SOC/IR, DFIR, threat hunting, vulnerability management, security automation, cloud/security operations, and AI security. His work focuses on practical security engineering, AI adoption risk, detection and response, and building controls that enable innovation without exposing sensitive data.
A19: Relevant background | B19: Details
A20: Focus areas | B20: AI Security, AppSec, Detection Engineering, Security Automation, Secure AI Adoption, LLM/Agentic AI Controls
A21: GitHub | B21: https://github.com/hamxas/AI-security-governance-checklist
A22: Version | B22: 1
A24: Framework alignment
A25: This tool is inspired by NIST AI RMF, NIST Generative AI Profile, ISO/IEC 42001, ISO/IEC 23894, OWASP LLM Top 10, MITRE ATLAS, EU AI Act concepts, and CSA AI Controls Matrix. It is an operational checklist, not an official certification or replacement for legal/regulatory advice.
A27: Attribution
A28: When sharing or reusing this workbook, please credit: Enterprise AI Security & Governance Checklist by Hamza Saleem.
A30: Disclaimer
A31: This workbook is provided for educational, assessment, and planning purposes. Organisations should tailor the controls to their own business context, regulatory environment, data classification model, and risk appetite.

Sheet Dashboard
A1: Enterprise AI Security & Governance Dashboard
A3: Metric | B3: Value
A4: Total Controls | B4: =COUNTA('Control Checklist'!$A$2:$A$69) -> 68
A5: Overall Maturity Score | B5: =IFERROR(AVERAGEIF('Control Checklist'!$K$2:$K$69,">=0",'Control Checklist'!$K$2:$K$69),0) -> 0
A6: Critical Controls Implemented/Tested | B6: =COUNTIFS('Control Checklist'!$I$2:$I$69,"Critical",'Control Checklist'!$K$2:$K$69,">=4") -> 0
A7: Controls Not Started | B7: =COUNTIF('Control Checklist'!$J$2:$J$69,"Not Started") -> 68
A10: Domain | B10: Control Count | C10: Avg Score | D10: Maturity Level | F10: Status | G10: Count
A11: AI Use Case Inventory | B11: =COUNTIF('Control Checklist'!$B$2:$B$69,A11) -> 6 | C11: =IFERROR(AVERAGEIFS('Control Checklist'!$K$2:$K$69,'Control Checklist'!$B$2:$B$69,A11),0) -> 0 | D11: =IF(C11>=4,"Strong",IF(C11>=3,"Good",IF(C11>=2,"Developing",IF(C11>=1,"Early","Not Started")))) -> Not Started | F11: Not Started | G11: =COUNTIF('Control Checklist'!$J$2:$J$69,F11) -> 68
A12: Agentic AI Controls | B12: =COUNTIF('Control Checklist'!$B$2:$B$69,A12) -> 6 | C12: =IFERROR(AVERAGEIFS('Control Checklist'!$K$2:$K$69,'Control Checklist'!$B$2:$B$69,A12),0) -> 0 | D12: =IF(C12>=4,"Strong",IF(C12>=3,"Good",IF(C12>=2,"Developing",IF(C12>=1,"Early","Not Started")))) -> Not Started | F12: Planned | G12: =COUNTIF('Control Checklist'!$J$2:$J$69,F12) -> 0
A13: Approved AI Tools & Access | B13: =COUNTIF('Control Checklist'!$B$2:$B$69,A13) -> 6 | C13: =IFERROR(AVERAGEIFS('Control Checklist'!$K$2:$K$69,'Control Checklist'!$B$2:$B$69,A13),0) -> 0 | D13: =IF(C13>=4,"Strong",IF(C13>=3,"Good",IF(C13>=2,"Developing",IF(C13>=1,"Early","Not Started")))) -> Not Started | F13: Partial | G13: =COUNTIF('Control Checklist'!$J$2:$J$69,F13) -> 0
A14: Data Classification & Privacy | B14: =COUNTIF('Control Checklist'!$B$2:$B$69,A14) -> 6 | C14: =IFERROR(AVERAGEIFS('Control Checklist'!$K$2:$K$69,'Control Checklist'!$B$2:$B$69,A14),0) -> 0 | D14: =IF(C14>=4,"Strong",IF(C14>=3,"Good",IF(C14>=2,"Developing",IF(C14>=1,"Early","Not Started")))) -> Not Started | F14: Implemented | G14: =COUNTIF('Control Checklist'!$J$2:$J$69,F14) -> 0
A15: Governance & Operating Model | B15: =COUNTIF('Control Checklist'!$B$2:$B$69,A15) -> 6 | C15: =IFERROR(AVERAGEIFS('Control Checklist'!$K$2:$K$69,'Control Checklist'!$B$2:$B$69,A15),0) -> 0 | D15: =IF(C15>=4,"Strong",IF(C15>=3,"Good",IF(C15>=2,"Developing",IF(C15>=1,"Early","Not Started")))) -> Not Started | F15: Implemented & Tested | G15: =COUNTIF('Control Checklist'!$J$2:$J$69,F15) -> 0
A16: LLM Gateway & Guardrails | B16: =COUNTIF('Control Checklist'!$B$2:$B$69,A16) -> 7 | C16: =IFERROR(AVERAGEIFS('Control Checklist'!$K$2:$K$69,'Control Checklist'!$B$2:$B$69,A16),0) -> 0 | D16: =IF(C16>=4,"Strong",IF(C16>=3,"Good",IF(C16>=2,"Developing",IF(C16>=1,"Early","Not Started")))) -> Not Started | F16: Automated & Monitored | G16: =COUNTIF('Control Checklist'!$J$2:$J$69,F16) -> 0
A17: Legal & Compliance | B17: =COUNTIF('Control Checklist'!$B$2:$B$69,A17) -> 4 | C17: =IFERROR(AVERAGEIFS('Control Checklist'!$K$2:$K$69,'Control Checklist'!$B$2:$B$69,A17),0) -> 0 | D17: =IF(C17>=4,"Strong",IF(C17>=3,"Good",IF(C17>=2,"Developing",IF(C17>=1,"Early","Not Started")))) -> Not Started | F17: N/A | G17: =COUNTIF('Control Checklist'!$J$2:$J$69,F17) -> 0
A18: Monitoring, Detection & Response | B18: =COUNTIF('Control Checklist'!$B$2:$B$69,A18) -> 7 | C18: =IFERROR(AVERAGEIFS('Control Checklist'!$K$2:$K$69,'Control Checklist'!$B$2:$B$69,A18),0) -> 0 | D18: =IF(C18>=4,"Strong",IF(C18>=3,"Good",IF(C18>=2,"Developing",IF(C18>=1,"Early","Not Started")))) -> Not Started
A19: RAG & Knowledge Controls | B19: =COUNTIF('Control Checklist'!$B$2:$B$69,A19) -> 5 | C19: =IFERROR(AVERAGEIFS('Control Checklist'!$K$2:$K$69,'Control Checklist'!$B$2:$B$69,A19),0) -> 0 | D19: =IF(C19>=4,"Strong",IF(C19>=3,"Good",IF(C19>=2,"Developing",IF(C19>=1,"Early","Not Started")))) -> Not Started
A20: Secure AI Development & SDLC | B20: =COUNTIF('Control Checklist'!$B$2:$B$69,A20) -> 6 | C20: =IFERROR(AVERAGEIFS('Control Checklist'!$K$2:$K$69,'Control Checklist'!$B$2:$B$69,A20),0) -> 0 | D20: =IF(C20>=4,"Strong",IF(C20>=3,"Good",IF(C20>=2,"Developing",IF(C20>=1,"Early","Not Started")))) -> Not Started
A21: Training & Change Management | B21: =COUNTIF('Control Checklist'!$B$2:$B$69,A21) -> 4 | C21: =IFERROR(AVERAGEIFS('Control Checklist'!$K$2:$K$69,'Control Checklist'!$B$2:$B$69,A21),0) -> 0 | D21: =IF(C21>=4,"Strong",IF(C21>=3,"Good",IF(C21>=2,"Developing",IF(C21>=1,"Early","Not Started")))) -> Not Started
A22: Vendor & Third-Party Risk | B22: =COUNTIF('Control Checklist'!$B$2:$B$69,A22) -> 5 | C22: =IFERROR(AVERAGEIFS('Control Checklist'!$K$2:$K$69,'Control Checklist'!$B$2:$B$69,A22),0) -> 0 | D22: =IF(C22>=4,"Strong",IF(C22>=3,"Good",IF(C22>=2,"Developing",IF(C22>=1,"Early","Not Started")))) -> Not Started

Sheet How to Use
A1: Enterprise AI Adoption Security & Governance Checklist
A2: Purpose | B2: Use this workbook to assess whether an organization can adopt AI safely while controlling data leakage, Shadow AI, LLM application risks, agentic workflows, vendor risk, and incident response.
A3: How to score controls | B3: Update the Status column in the Control Checklist. Scores are formula-driven: Not Started=0, Planned=1, Partial=2, Implemented=3, Implemented & Tested=4, Automated & Monitored=5, N/A excluded.
A4: Suggested workflow | B4: 1) Fill AI Asset Inventory. 2) Review Guardrails Matrix. 3) Complete Control Checklist. 4) Add detections in Detection Library. 5) Review Dashboard for maturity gaps.
A5: Target users | B5: Security architects, AppSec engineers, SOC/detection engineers, GRC, privacy, platform engineering, and AI product owners.
A6: Important note | B6: This is an assessment and planning aid, not legal advice or a certification replacement. Validate regulatory obligations with legal/compliance teams.
A8: Score | B8: Meaning
A9: 0 | B9: Not implemented
A10: 1 | B10: Planned but not implemented
A11: 2 | B11: Partially implemented or inconsistent
A12: 3 | B12: Implemented
A13: 4 | B13: Implemented and tested
A14: 5 | B14: Automated, monitored, and continuously improved

Sheet Control Checklist
A1: Control ID | B1: Domain | C1: Control | D1: Implementation Question | E1: Risk Addressed | F1: Framework Mapping | G1: Evidence to Collect | H1: Owner | I1: Priority | J1: Status | K1: Score | L1: Target Date | M1: Notes | N1: Source URL
A2: GOV-01 | B2: Governance & Operating Model | C2: AI governance ownership | D2: Is there a named executive owner and accountable AI risk forum for enterprise AI adoption? | E2: Unclear accountability and uncontrolled AI adoption | F2: NIST AI RMF Govern; ISO/IEC 42001 AIMS governance | G2: AI governance charter, RACI, steering forum minutes | H2: CISO / AI Governance Lead | I2: Critical | J2: Not Started | K2: =IF(J2="N/A","",IF(J2="Not Started",0,IF(J2="Planned",1,IF(J2="Partial",2,IF(J2="Implemented",3,IF(J2="Implemented & Tested",4,IF(J2="Automated & Monitored",5,""))))))) -> 0 | N2: https://www.nist.gov/itl/ai-risk-management-framework
A3: GOV-02 | B3: Governance & Operating Model | C3: AI acceptable use policy | D3: Is there a practical AI use policy defining approved tools, prohibited data, and escalation routes? | E3: Shadow AI, data leakage, misuse | F3: NIST AI RMF Govern; ISO/IEC 42001 policies | G3: Published policy, user attestation, comms evidence | H3: Security / Legal | I3: Critical | J3: Not Started | K3: =IF(J3="N/A","",IF(J3="Not Started",0,IF(J3="Planned",1,IF(J3="Partial",2,IF(J3="Implemented",3,IF(J3="Implemented & Tested",4,IF(J3="Automated & Monitored",5,""))))))) -> 0 | N3: https://www.iso.org/standard/42001
A4: GOV-03 | B4: Governance & Operating Model | C4: AI risk appetite | D4: Has leadership defined which AI risks are acceptable, conditional, or prohibited? | E4: Inconsistent decisions and uncontrolled exceptions | F4: NIST AI RMF Govern; ISO/IEC 23894 | G4: Risk appetite statement, exception process | H4: Risk / Compliance | I4: High | J4: Not Started | K4: =IF(J4="N/A","",IF(J4="Not Started",0,IF(J4="Planned",1,IF(J4="Partial",2,IF(J4="Implemented",3,IF(J4="Implemented & Tested",4,IF(J4="Automated & Monitored",5,""))))))) -> 0 | N4: https://www.iso.org/standard/77304.html
A5: GOV-04 | B5: Governance & Operating Model | C5: AI control ownership | D5: Are control owners assigned for DLP, gateway, identity, SOC, AppSec, vendor risk, and privacy controls? | E5: Control gaps due to unclear ownership | F5: ISO/IEC 42001; CSA AICM | G5: Control owner register, RACI | H5: Security Leadership | I5: High | J5: Not Started | K5: =IF(J5="N/A","",IF(J5="Not Started",0,IF(J5="Planned",1,IF(J5="Partial",2,IF(J5="Implemented",3,IF(J5="Implemented & Tested",4,IF(J5="Automated & Monitored",5,""))))))) -> 0 | N5: https://cloudsecurityalliance.org/artifacts/ai-controls-matrix-v1-1
A6: GOV-05 | B6: Governance & Operating Model | C6: AI exception process | D6: Is there a documented exception process for high-risk AI use cases and blocked data types? | E6: Business bypasses controls without risk acceptance | F6: NIST AI RMF Manage; ISO/IEC 23894 | G6: Risk acceptance records, approval workflow | H6: Risk / Security | I6: Medium | J6: Not Started | K6: =IF(J6="N/A","",IF(J6="Not Started",0,IF(J6="Planned",1,IF(J6="Partial",2,IF(J6="Implemented",3,IF(J6="Implemented & Tested",4,IF(J6="Automated & Monitored",5,""))))))) -> 0 | N6: https://www.nist.gov/itl/ai-risk-management-framework
A7: GOV-06 | B7: Governance & Operating Model | C7: AI metrics and reporting | D7: Are AI usage, risk, incidents, exceptions, and control maturity reported to leadership? | E7: Leadership lacks visibility into AI risk | F7: NIST AI RMF Govern/Manage; ISO/IEC 42001 monitoring | G7: Monthly dashboard, KRIs/KPIs | H7: Security Governance | I7: Medium | J7: Not Started | K7: =IF(J7="N/A","",IF(J7="Not Started",0,IF(J7="Planned",1,IF(J7="Partial",2,IF(J7="Implemented",3,IF(J7="Implemented & Tested",4,IF(J7="Automated & Monitored",5,""))))))) -> 0 | N7: https://www.iso.org/standard/42001
A8: INV-01 | B8: AI Use Case Inventory | C8: AI use case inventory | D8: Is there an inventory of approved AI tools, internal AI apps, RAG systems, coding assistants, and agents? | E8: Unknown AI estate | F8: NIST AI RMF Map; ISO/IEC 23894 | G8: AI asset register | H8: Security Architecture | I8: Critical | J8: Not Started | K8: =IF(J8="N/A","",IF(J8="Not Started",0,IF(J8="Planned",1,IF(J8="Partial",2,IF(J8="Implemented",3,IF(J8="Implemented & Tested",4,IF(J8="Automated & Monitored",5,""))))))) -> 0 | N8: https://www.nist.gov/itl/ai-risk-management-framework
A9: INV-02 | B9: AI Use Case Inventory | C9: AI data flow mapping | D9: Are data inputs, outputs, storage, retention, and external model destinations documented for each AI use case? | E9: Unknown sensitive data exposure | F9: NIST AI RMF Map; ISO/IEC 23894 | G9: Data flow diagrams, architecture docs | H9: Platform / Data | I9: Critical | J9: Not Started | K9: =IF(J9="N/A","",IF(J9="Not Started",0,IF(J9="Planned",1,IF(J9="Partial",2,IF(J9="Implemented",3,IF(J9="Implemented & Tested",4,IF(J9="Automated & Monitored",5,""))))))) -> 0 | N9: https://www.iso.org/standard/77304.html
A10: INV-03 | B10: AI Use Case Inventory | C10: Model/provider register | D10: Are model providers, regions, retention settings, training-use terms, and contract status documented? | E10: Unapproved provider or unsafe data handling | F10: NIST AI RMF Map; Vendor risk | G10: Provider register, contract summary | H10: Procurement / Security | I10: High | J10: Not Started | K10: =IF(J10="N/A","",IF(J10="Not Started",0,IF(J10="Planned",1,IF(J10="Partial",2,IF(J10="Implemented",3,IF(J10="Implemented & Tested",4,IF(J10="Automated & Monitored",5,""))))))) -> 0 | N10: https://www.nist.gov/publications/artificial-intelligence-risk-management-framework-generative-artificial-intelligence
A11: INV-04 | B11: AI Use Case Inventory | C11: Shadow AI discovery | D11: Are unapproved AI tools discovered through SWG/CASB/DNS/endpoint/SaaS expense data? | E11: Uncontrolled AI adoption and data leakage | F11: NIST AI RMF Measure; CSA AICM | G11: Shadow AI dashboard, SWG/CASB reports | H11: SOC / Security Engineering | I11: Critical | J11: Not Started | K11: =IF(J11="N/A","",IF(J11="Not Started",0,IF(J11="Planned",1,IF(J11="Partial",2,IF(J11="Implemented",3,IF(J11="Implemented & Tested",4,IF(J11="Automated & Monitored",5,""))))))) -> 0 | N11: https://cloudsecurityalliance.org/artifacts/ai-controls-matrix-v1-1
A12: INV-05 | B12: AI Use Case Inventory | C12: Risk tiering | D12: Is every AI use case assigned a risk tier based on data sensitivity, user base, external exposure, autonomy, and impact? | E12: High-risk systems treated like low-risk tools | F12: NIST AI RMF Map/Measure; EU AI Act risk-based approach | G12: Risk tiering results | H12: Risk / Product Security | I12: High | J12: Not Started | K12: =IF(J12="N/A","",IF(J12="Not Started",0,IF(J12="Planned",1,IF(J12="Partial",2,IF(J12="Implemented",3,IF(J12="Implemented & Tested",4,IF(J12="Automated & Monitored",5,""))))))) -> 0 | N12: https://digital-strategy.ec.europa.eu/en/policies/regulatory-framework-ai
A13: INV-06 | B13: AI Use Case Inventory | C13: Lifecycle status | D13: Is each AI asset tracked from prototype to production, retirement, and periodic review? | E13: Prototype AI becomes production without controls | F13: ISO/IEC 42001 lifecycle management | G13: Lifecycle register, review dates | H13: AI Product Owner | I13: Medium | J13: Not Started | K13: =IF(J13="N/A","",IF(J13="Not Started",0,IF(J13="Planned",1,IF(J13="Partial",2,IF(J13="Implemented",3,IF(J13="Implemented & Tested",4,IF(J13="Automated & Monitored",5,""))))))) -> 0 | N13: https://www.iso.org/standard/42001
... A69: CMP-04 | B69: Legal & Compliance | C69: Auditability and evidence | D69: Is evidence retained for AI risk decisions, control tests, vendor approvals, and incident handling? | E69: Cannot prove governance/control operation | F69: ISO/IEC 42001; NIST AI RMF Govern | G69: Evidence register | H69: Compliance | I69: High | J69: Not Started | K69: =IF(J69="N/A","",IF(J69="Not Started",0,IF(J69="Planned",1,IF(J69="Partial",2,IF(J69="Implemented",3,IF(J69="Implemented & Tested",4,IF(J69="Automated & Monitored",5,""))))))) -> 0 | N69: https://www.iso.org/standard/42001

Sheet AI Asset Inventory
A1: AI Asset ID | B1: AI Use Case / Tool | C1: Owner | D1: Business Function | E1: User Group | F1: AI Type | G1: Provider / Model | H1: Internal or External | I1: Data Classification | J1: File Uploads? | K1: RAG? | L1: Agent / Tool Use? | M1: Risk Tier | N1: Current Controls | O1: Key Gaps | P1: Review Status | Q1: Next Review | R1: Notes
A2: AI-001 | B2: Example: Enterprise AI Chat Portal | C2: Security / Platform | D2: All business functions | E2: All employees | F2: Chat / document assistant | G2: Claude / GPT via approved gateway | H2: External model via approved gateway | I2: Internal | J2: Yes | K2: Optional | L2: No | M2: Medium | N2: SSO, DLP, logging, model allowlist | O2: Output filtering and SIEM detections not fully tuned | P2: Planned | R2: Replace this row with your own asset
A3: AI-002 | B3: Example: Developer Coding Assistant | C3: Engineering | D3: Software Engineering | E3: Developers | F3: Coding assistant / CLI | G3: Approved coding model via gateway | H3: External model via gateway | I3: Confidential / Source Code | J3: No | K3: No | L3: Limited local tool use | M3: High | N3: SSO, repo allowlist, secret scanning | O3: Need endpoint process telemetry and PR risk checks | P3: Planned | R3: Replace this row with your own asset

Sheet Guardrails Matrix
A1: Data / Use Case | B1: Public | C1: Internal | D1: Confidential | E1: Restricted | F1: Secrets / Credentials | G1: Recommended Control Pattern | H1: Notes
A2: General Q&A / brainstorming | B2: Allow | C2: Allow | D2: Warn | E2: Block | F2: Block | G2: Enterprise AI workspace or portal with logging | H2: Use approved tools; no personal accounts.
A3: Email drafting | B3: Allow | C3: Allow | D3: Redact | E3: Exception Required | F3: Block | G3: DLP + user warning + no vendor training | H3: Watch for customer/HR/legal context.
A4: Document summarisation | B4: Allow | C4: Allow | D4: Redact / Tokenize | E4: Exception Required | F4: Block | G4: File DLP + data classification + retention rules | H4: Large uploads should be logged.
A5: Code assistance | B5: Allow | C5: Allow | D5: Warn | E5: Block | F5: Block | G5: Approved coding assistant/gateway + secret scanning | H5: Block .env, keys, private code to unapproved tools.
A6: Customer support analysis | B6: Allow | C6: Redact | D6: Tokenize | E6: Exception Required | F6: Block | G6: Approved workflow with PII tokenization and audit | H6: Use case-specific approval required.
A7: RAG knowledge search | B7: Allow | C7: Allow | D7: Allow with ACLs | E7: Exception Required | F7: Block | G7: RAG ACL inheritance + source citation + retrieval logs | H7: Do not index restricted sources by default.
A8: Agent sends email / changes ticket | B8: Allow | C8: Warn | D8: Human Approval | E8: Exception Required | F8: Block | G8: Tool permission broker + human-in-loop | H8: Agent actions must be auditable.
A9: Agent modifies cloud/production | B9: Block | C9: Exception Required | D9: Exception Required | E9: Block | F9: Block | G9: No direct production changes unless formal change approval | H9: Usually too risky for general adoption.

Sheet Detection Library
A1: Detection ID | B1: Detection Use Case | C1: Primary Log Sources | D1: Logic / Signal | E1: Severity | F1: Response Action | G1: Mapped Risk | H1: Framework Mapping | I1: Status | J1: Owner | K1: Notes
A2: DET-AI-001 | B2: Sensitive data sent to public AI | C2: SWG/CASB, DLP, Identity | D2: Prompt/upload to unapproved AI domain contains PII, confidential keywords, source code, or classified labels | E2: Critical | F2: Block or warn; alert SOC; notify data owner | G2: Data leakage | H2: NIST GenAI Profile; OWASP LLM06 | I2: Planned | J2: SOC / DLP | K2: Tune DLP to reduce false positives.
A3: DET-AI-002 | B3: Secrets pasted into AI | C3: DLP, gateway logs, secret scanner | D3: AWS/GCP/Azure keys, GitHub tokens, private keys, JWTs, .env patterns in prompt/file | E3: Critical | F3: Block; create incident; rotate secret | G3: Credential leakage | H3: OWASP LLM06; NIST GenAI Profile | I3: Planned | J3: Security Engineering | K3: Use trufflehog/detect-secrets patterns.
A4: DET-AI-003 | B4: Unapproved AI SaaS usage | C4: SWG/CASB, DNS, firewall | D4: User accesses known AI tool not in approved catalogue | E4: High | F4: Warn/block based on phase; route to approved portal | G4: Shadow AI | H4: NIST AI RMF Measure; CSA AICM | I4: Planned | J4: Network Security | K4: Start in monitor-only mode.
A5: DET-AI-004 | B5: Risky AI OAuth grant | C5: Google/M365/Okta/GitHub audit logs | D5: New OAuth app with AI-related name requests Drive/Gmail/Slack/GitHub read/write scopes | E5: Critical | F5: Revoke or approve; investigate user/data access | G5: SaaS data exposure | H5: CSA AICM; NIST GenAI Profile | I5: Planned | J5: SaaS Security | K5: Maintain approved app list.
A6: DET-AI-005 | B6: Prompt injection attempt | C6: LLM gateway/app logs | D6: Prompt contains instruction override, system prompt request, exfiltrate docs, bypass controls, jailbreak indicators | E6: Medium | F6: Log/alert; block if targeting internal/RAG app | G6: Prompt injection | H6: OWASP LLM01; MITRE ATLAS | I6: Planned | J6: AppSec / SOC | K6: Classifier + pattern detection.
A7: DET-AI-006 | B7: RAG ACL violation attempt | C7: RAG retrieval logs, identity logs | D7: User retrieves or requests documents outside their source-system permissions | E7: Critical | F7: Block response; incident; fix ACL/index | G7: Unauthorized data access | H7: OWASP LLM06; NIST AI RMF Measure | I7: Planned | J7: AI Platform | K7: Requires document IDs in logs.
A8: DET-AI-007 | B8: Agent risky tool call | C8: Agent logs, API logs, IAM logs | D8: Agent calls email/send, db export, cloud modify, delete, production commands, or unusual tool chain | E8: Critical | F8: Require approval; alert SOC | G8: Excessive agency | H8: OWASP LLM08; MITRE ATLAS | I8: Planned | J8: AI Platform / SOC | K8: Separate read/write tools.
A9: DET-AI-008 | B9: LLM API abuse/cost spike | C9: Gateway logs, billing, API gateway | D9: High token volume, unusual model, repeated failures, new client/app, abnormal cost | E9: Medium | F9: Throttle; investigate key; rotate if needed | G9: Model DoS / abuse | H9: OWASP LLM04 | I9: Planned | J9: AI Platform | K9: Use per-user budget baselines.
A10: DET-AI-009 | B10: AI browser extension risk | C10: MDM, browser management, EDR | D10: Extension with read-all-sites, clipboard, Gmail/Drive, internal app access, or unknown publisher | E10: High | F10: Block/remove; notify user; review extension | G10: Shadow AI / data exposure | H10: CSA AICM | I10: Planned | J10: Endpoint / IT | K10: High value control.
A11: DET-AI-010 | B11: AI-generated insecure code in PR | C11: GitHub/GitLab, CI/CD, SAST/SCA/secrets | D11: PR after AI-assisted coding adds insecure pattern, secret, unsafe dependency, auth/IAM change | E11: High | F11: Block merge; AppSec review | G11: Insecure output handling / supply chain | H11: OWASP LLM02/LLM05 | I11: Planned | J11: AppSec / DevSecOps | K11: Focus on critical repos first.

Sheet Vendor Review
A1: Question ID | B1: Review Area | C1: Question | D1: Risk if Weak | E1: Evidence / Expected Answer | F1: Priority | G1: Status | H1: Notes
A2: VR-01 | B2: Data Use | C2: Does the vendor use customer prompts/files/responses to train models by default? | D2: Company data could improve external models | E2: No training on company data; contractual commitment | F2: Critical | G2: Not Started
A3: VR-02 | B3: Retention | C3: What is the prompt/file/response retention period and can it be configured? | D3: Sensitive data retained too long | E3: Retention period documented; configurable; deletion process | F3: Critical | G3: Not Started
A4: VR-03 | B4: Access Control | C4: Does the product support SSO, SCIM, MFA, RBAC, and admin roles? | D4: Unmanaged account access | E4: SSO/SCIM enabled; roles documented | F4: High | G4: Not Started
A5: VR-04 | B5: Logging | C5: What audit logs are available and can they be exported to SIEM? | D5: No investigation evidence | E5: User/model/file/action logs exportable | F5: High | G5: Not Started
A6: VR-05 | B6: Data Residency | C6: Where is data processed and stored? | D6: Regulatory or contractual violation | E6: Regions documented and approved | F6: High | G6: Not Started
A7: VR-06 | B7: Subprocessors | C7: Which subprocessors can access AI data? | D7: Unknown third-party exposure | E7: Subprocessor list and notification process | F7: High | G7: Not Started
A8: VR-07 | B8: Security Testing | C8: Does vendor provide SOC 2/ISO 27001, pen test summary, vulnerability process, and incident notification SLA? | D8: Weak vendor security assurance | E8: Reports reviewed and acceptable | F8: High | G8: Not Started
A9: VR-08 | B9: Model Controls | C9: Can admins restrict models, features, connectors, file uploads, and external sharing? | D9: Users bypass safe usage rules | E9: Admin controls tested | F9: High | G9: Not Started
A10: VR-09 | B10: Connectors/OAuth | C10: What scopes are required for Google/M365/Slack/GitHub/Jira connectors? | D10: Overbroad data access | E10: Least-privilege scopes documented | F10: Critical | G10: Not Started
A11: VR-10 | B11: Incident Response | C11: How will the vendor notify and support investigation of AI/data incidents? | D11: Delayed breach response | E11: Incident process and SLA in contract | F11: High | G11: Not Started

Sheet Incident Playbook
A1: Phase | B1: Step | C1: Action | D1: Owner | E1: Evidence / Logs | F1: Notes
A2: Prepare | B2: 1 | C2: Define AI incident categories: data leakage, secrets in prompt, prompt injection, RAG leak, agent misuse, AI API key abuse | D2: SOC / IR | E2: Incident taxonomy
A3: Detect | B3: 2 | C3: Correlate AI gateway, DLP, SWG/CASB, identity, OAuth, endpoint, Git, and cloud logs | D3: SOC | E3: SIEM alert, DLP event, gateway request ID
A4: Triage | B4: 3 | C4: Identify user, app/tool, model provider, data involved, classification, action taken, and whether data reached external provider | D4: SOC / Data Owner | E4: Prompt metadata, file hash, DLP classification | F4: Avoid over-retaining sensitive prompt content.
A5: Contain | B5: 4 | C5: Block AI tool/app, revoke OAuth app, suspend API key, disable connector, or isolate endpoint if needed | D5: Security Engineering | E5: Policy change, revoke record
A6: Eradicate | B6: 5 | C6: Rotate leaked credentials, remove exposed documents from index, fix RAG ACLs, patch agent tool permissions | D6: AppSec / Platform | E6: Rotation ticket, PR, config diff
A7: Notify | B7: 6 | C7: Notify privacy/legal/compliance if personal data, customer data, or regulated data was involved | D7: IR Lead / Legal | E7: Notification decision log
A8: Recover | B8: 7 | C8: Restore safe AI access through approved path and verify guardrails/detections are working | D8: Platform / SOC | E8: Test evidence
A9: Lessons Learned | B9: 8 | C9: Update policies, guardrails, detections, user coaching, and vendor controls | D9: AI Security | E9: Post-incident report

Sheet Reference Sources
A1: Framework / Source | B1: What it supports in this workbook | C1: URL
A2: NIST AI Risk Management Framework (AI RMF 1.0) | B2: Govern / Map / Measure / Manage structure for AI risk management | C2: https://www.nist.gov/itl/ai-risk-management-framework
A3: NIST AI 600-1 Generative AI Profile | B3: Generative AI-specific risk actions, incident communications, content provenance, data leakage, security testing | C3: https://www.nist.gov/publications/artificial-intelligence-risk-management-framework-generative-artificial-intelligence
A4: ISO/IEC 42001:2023 | B4: AI management system governance, roles, policies, monitoring, continual improvement | C4: https://www.iso.org/standard/42001
A5: ISO/IEC 23894:2023 | B5: AI-specific risk management process and integration with organizational risk management | C5: https://www.iso.org/standard/77304.html
A6: OWASP Top 10 for LLM Applications 2025 | B6: Technical LLM application risks: prompt injection, sensitive information disclosure, excessive agency, supply chain | C6: https://genai.owasp.org/llm-top-10/
A7: MITRE ATLAS | B7: Adversarial AI tactics and techniques for detection and threat modelling | C7: https://atlas.mitre.org/
A8: EU AI Act | B8: Risk-based AI regulatory classification and high-risk system lifecycle controls | C8: https://digital-strategy.ec.europa.eu/en/policies/regulatory-framework-ai
A9: Cloud Security Alliance AI Controls Matrix | B9: Cloud-based AI control categories and operational control mapping | C9: https://cloudsecurityalliance.org/artifacts/ai-controls-matrix-v1-1
A11: Tool Author | B11: Hamza Saleem | C11: https://github.com/hamxas/AI-security-governance-checklist
A12: Attribution | B12: Enterprise AI Security & Governance Checklist by Hamza Saleem | C12: Reuse with attribution.
A13: Version | B13: 1.1 | C13: Branded introduction page added.

Sheet Settings
A1: Status Values | C1: Priority Values | E1: Risk Tier Values | G1: Data Classification | I1: Guardrail Decision
A2: Not Started | C2: Critical | E2: Low | G2: Public | I2: Allow
A3: Planned | C3: High | E3: Medium | G3: Internal | I3: Warn
A4: Partial | C4: Medium | E4: High | G4: Confidential | I4: Redact
A5: Implemented | C5: Low | E5: Critical | G5: Restricted | I5: Tokenize
A6: Implemented & Tested | G6: Secrets/Credentials | I6: Block
A7: Automated & Monitored | I7: Exception Required
A8: N/A
